LICENSE
MANIFEST.in
README.md
setup.cfg
setup.py
filtus/AutEx.py
filtus/DataContainer.py
filtus/Filter.py
filtus/Filtus.py
filtus/FiltusAnalysis.py
filtus/FiltusDatabase.py
filtus/FiltusQC.py
filtus/FiltusUtils.py
filtus/FiltusWidgets.py
filtus/InputDialog.py
filtus/VariantFileReader.py
filtus/__init__.py
filtus/autorun.py
filtus/data
filtus/man
filtus/testfiles
filtus.egg-info/PKG-INFO
filtus.egg-info/SOURCES.txt
filtus.egg-info/dependency_links.txt
filtus.egg-info/entry_points.txt
filtus.egg-info/requires.txt
filtus.egg-info/top_level.txt
filtus/data/DecodeMap_thin.txt
filtus/data/genelengths.txt
filtus/man/autex.html
filtus/man/database.html
filtus/man/denovo.html
filtus/man/familybased.html
filtus/man/filters.html
filtus/man/filtus.html
filtus/man/genesharing.html
filtus/man/loading.html
filtus/man/pictures
filtus/man/qcplots.html
filtus/man/usermanual.html
filtus/man/pictures/advancedload.png
filtus/man/pictures/autex.png
filtus/man/pictures/denovo.png
filtus/man/pictures/filter_area.png
filtus/man/pictures/genesharing.png
filtus/man/pictures/inputsettings.png
filtus/man/pictures/qcplots.png
filtus/testfiles/CSQ_test.vcf
filtus/testfiles/denovo_tests.vcf
filtus/testfiles/test1.csv
filtus/testfiles/test2.csv
filtus/testfiles/test_file.csv
filtus/testfiles/trioHG002_22X.vcf
filtus/testfiles/vcf_test.vcf