Metadata-Version: 1.1
Name: filtus
Version: 1.0.5
Summary: Analysis of exome variant files
Home-page: https://github.com/magnusdv/filtus
Author: Magnus Dehli Vigeland
Author-email: magnusdv@medisin.uio.no
License: GPL-2
Keywords: exome,variant filtering,vcf,de novo,autozygosity mapping
Platform: UNKNOWN
Classifier: Programming Language :: Python :: 2.7
Classifier: License :: OSI Approved :: GNU General Public License v2 or later (GPLv2+)
